stpyvista/__init__.py
stpyvista/dataview.py
stpyvista/panel_backend.py
stpyvista/trame_backend.py
stpyvista/utils.py
stpyvista/vtkjs_backend.py
stpyvista/panel_based/fullscreen.js
stpyvista/panel_based/index.html
stpyvista/panel_based/main.js
stpyvista/panel_based/streamlit-component-lib.js
stpyvista/panel_based/style.css
stpyvista/trame_based/index.html
stpyvista/trame_based/main.js
stpyvista/trame_based/streamlit-component-lib.js
stpyvista/vanilla_vtkjs/index.html
stpyvista/vanilla_vtkjs/main.js
stpyvista/vanilla_vtkjs/streamlit-component-lib.js
stpyvista-0.1.3.dist-info/METADATA
stpyvista-0.1.3.dist-info/WHEEL
stpyvista-0.1.3.dist-info/licenses/LICENSE
stpyvista-0.1.3.dist-info/RECORD
